[
  {
    "id": 1,
    "name": "Turtle Neck",
    "imgUrl": "https://nhatminhdecor.com/wp-content/uploads/2019/01/chup-anh-voi-mau-that-800x800.jpg",
    "price": "60",
    "salePrice": "40"
  },
  {
    "id": 2,
    "name": "T-Shirt",
    "imgUrl": "https://tronhouse.com/assets/data/editor/source/nhung-cach-chup-hinh-quan-ao-duoc-uu-chuong-nhat/chup-hinh-sang-tao-1.jpg",
    "price": "50",
    "salePrice": "45"
  },
  {
    "id": 3,
    "name": "Jumper",
    "imgUrl": "https://nhatminhdecor.com/wp-content/uploads/2019/01/chup-anh-san-pham-quan-ao-800x800.jpg",
    "price": "100",
    "salePrice": "80"
  },
  {
    "id": 4,
    "name": "Sweater",
    "imgUrl": "https://nhatminhdecor.com/wp-content/uploads/2019/01/chup-anh-voi-phong-pvc-800x800.jpg",
    "price": "80",
    "salePrice": "45"
  },
  {
    "id": 5,
    "name": "Dress",
    "imgUrl": "https://i.pinimg.com/236x/b4/fd/d6/b4fdd67095d6a8cfd7dbf760919ba89b.jpg",
    "price": "80",
    "salePrice": "45"
  },
  {
    "id": 6,
    "name": "Women Corset Top",
    "imgUrl": "https://nhatminhdecor.com/wp-content/uploads/2019/01/chup-anh-san-pham-quan-ao-2-800x800.jpg",
    "price": "80",
    "salePrice": "45"
  },
  {
    "id": 7,
    "name": "Sweater",
    "imgUrl": "https://nhatminhdecor.com/wp-content/uploads/2019/01/chup-anh-voi-phong-nen-vai-trang.jpg",
    "price": "80",
    "salePrice": "45"
  },
  {
    "id": 8,
    "name": "Women Corset Top",
    "imgUrl": "https://nhatminhdecor.com/wp-content/uploads/2019/01/chup-anh-voi-phong-pvc-800x800.jpg",
    "price": "80",
    "salePrice": "45"
  },
  {
    "id": 9,
    "name": "Casual Solid Color Top",
    "imgUrl": "https://i5.walmartimages.com/seo/Vedolay-Shein-Tops-For-Women-Women-s-Casual-Shirts-Twist-Knot-Tunics-Tops-F-Navy-XXL_3a86592c-458c-4fcd-96fe-688c2d2f2695.0e32269be1ebcc68276d50e95f5a80e4.jpeg?odnHeight=768&odnWidth=768&odnBg=FFFFFF",
    "price": "80",
    "salePrice": "45"
  },
  {
    "id": 10,
    "name": "Women Corset Top",
    "imgUrl": "https://nhatminhdecor.com/wp-content/uploads/2019/01/chup-anh-voi-phong-pvc-800x800.jpg",
    "price": "80",
    "salePrice": "45"
  },
  {
    "id": 11,
    "name": "Embroidery Drawstring Front Puff Sleeve",
    "imgUrl": "https://i5.walmartimages.com/asr/2c3477ea-6765-43e3-9159-3a1e87b6da62.5e54397b77965de4880efa77991d4858.jpeg",
    "price": "80",
    "salePrice": "45"
  },
  {
    "id": 12,
    "name": "Women's Lantern Sleeve Floral Print Blouse",
    "imgUrl": "https://i5.walmartimages.com/asr/1def905f-4835-4d04-a97d-468c730fed45.ee7d0c176799d84c449130f11def1185.jpeg?odnHeight=768&odnWidth=768&odnBg=FFFFFF",
    "price": "100",
    "salePrice": "70"
  },
  {
    "id": 13,
    "name": "Off-shoulder Tie Front Frill Trim Blouse",
    "imgUrl": "https://d1flfk77wl2xk4.cloudfront.net/Assets/28/812/L_p0094281228.jpg",
    "price": "60",
    "salePrice": "40"
  },
  {
    "id": 14,
    "name": "Women's Off-Shoulder Striped Shirt",
    "imgUrl": "https://m.media-amazon.com/images/I/716+ESMGFZS._AC_UY350_.jpg",
    "price": "90",
    "salePrice": "80"
  },
  {
    "id": 15,
    "name": "Floral Print Ruffle Summer Short Dress",
    "imgUrl": "https://ae01.alicdn.com/kf/S87e76eea3460415ea3068603a21902edP.jpg_640x640Q90.jpg_.webp",
    "price": "160",
    "salePrice": "90"
  },
  {
    "id": 16,
    "name": "Floral Print Pleated Bust Slip Dress",
    "imgUrl": "https://images.asos-media.com/products/asos-design-mini-slip-dress-in-bright-floral-print/200306088-1-brightfloralprint?$n_640w$&wid=513&fit=constrain",
    "price": "80",
    "salePrice": "45"
  },
  {
    "id": 17,
    "name": "Solid Frill Trim Tie Front Tube Dress",
    "imgUrl": "",
    "price": "60",
    "salePrice": "45"
  },
  {
    "id": 18,
    "name": "Women's Wine Glass Printed Short Sleeve T-Shirt",
    "imgUrl": "https://canary.contestimg.wish.com/api/webimage/617a19a3676b6aea5dd57aa1-large.jpg?cache_buster=4c2caea2b117b376a35d56c9f5c38841",
    "price": "80",
    "salePrice": "45"
  },
  {
    "id": 19,
    "name": "Cherry Print Cropped Tank Top",
    "imgUrl": "https://m.media-amazon.com/images/I/612a4ExGc2L._AC_SL1000_.jpg",
    "price": "50",
    "salePrice": "45"
  },
  {
    "id": 20,
    "name": "Women Corset Top",
    "imgUrl": "https://nhatminhdecor.com/wp-content/uploads/2019/01/chup-anh-voi-phong-pvc-800x800.jpg",
    "price": "80",
    "salePrice": "45"
  }
]
